{"deterministic": true, "task": "cleaning_bedroom", "task_id": 0, "scene": "Beechwood_1_int", "task_done": true, "total_frame_num": 5200, "failed": false, "filename": "cleaning_bedroom_0_Beechwood_1_int_2021-09-10_21-59-25.hdf5", "segmentations": {"flat": {"start": 1, "end": 5060, "duration": 5059, "state_records": [], "sub_segments": [{"start": 1, "end": 522, "duration": 521, "state_records": [{"name": "InHandOfRobot", "objects": ["vacuum_105"], "value": true}], "sub_segments": []}, {"start": 522, "end": 771, "duration": 249, "state_records": [{"name": "OnFloor", "objects": ["sheet_107", "room_floor_bedroom_0"], "value": true}], "sub_segments": []}, {"start": 771, "end": 828, "duration": 57, "state_records": [{"name": "InHandOfRobot", "objects": ["sheet_107"], "value": true}], "sub_segments": []}, {"start": 828, "end": 960, "duration": 132, "state_records": [{"name": "OnTop", "objects": ["sheet_107", "bed_43"], "value": true}], "sub_segments": []}, {"start": 960, "end": 987, "duration": 27, "state_records": [{"name": "InHandOfRobot", "objects": ["painting_104"], "value": true}], "sub_segments": []}, {"start": 987, "end": 1006, "duration": 19, "state_records": [{"name": "OnTop", "objects": ["painting_104", "sheet_107"], "value": true}], "sub_segments": []}, {"start": 1006, "end": 1174, "duration": 168, "state_records": [{"name": "Open", "objects": ["bottom_cabinet_6"], "value": true}], "sub_segments": []}, {"start": 1174, "end": 1336, "duration": 162, "state_records": [{"name": "InHandOfRobot", "objects": ["cologne_103"], "value": true}], "sub_segments": []}, {"start": 1336, "end": 1382, "duration": 46, "state_records": [{"name": "Inside", "objects": ["cologne_103", "bottom_cabinet_6"], "value": true}], "sub_segments": []}, {"start": 1382, "end": 1384, "duration": 2, "state_records": [{"name": "OnTop", "objects": ["cologne_103", "bottom_cabinet_6"], "value": true}], "sub_segments": []}, {"start": 1384, "end": 1827, "duration": 443, "state_records": [{"name": "OnFloor", "objects": ["necklace_102", "room_floor_bedroom_0"], "value": true}], "sub_segments": []}, {"start": 1827, "end": 2222, "duration": 395, "state_records": [{"name": "InHandOfRobot", "objects": ["necklace_102"], "value": true}], "sub_segments": []}, {"start": 2222, "end": 2389, "duration": 167, "state_records": [{"name": "Inside", "objects": ["necklace_102", "bottom_cabinet_6"], "value": true}], "sub_segments": []}, {"start": 2389, "end": 2392, "duration": 3, "state_records": [{"name": "OnTop", "objects": ["necklace_102", "bottom_cabinet_6"], "value": true}], "sub_segments": []}, {"start": 2392, "end": 2748, "duration": 356, "state_records": [{"name": "InHandOfRobot", "objects": ["vacuum_105"], "value": true}], "sub_segments": []}, {"start": 2748, "end": 3082, "duration": 334, "state_records": [{"name": "OnFloor", "objects": ["bottom_cabinet_1", "room_floor_bedroom_0"], "value": true}], "sub_segments": []}, {"start": 3082, "end": 3142, "duration": 60, "state_records": [{"name": "Open", "objects": ["bottom_cabinet_1"], "value": true}], "sub_segments": []}, {"start": 3142, "end": 3215, "duration": 73, "state_records": [{"name": "InHandOfRobot", "objects": ["jeans_101"], "value": true}], "sub_segments": []}, {"start": 3215, "end": 3261, "duration": 46, "state_records": [{"name": "OnTop", "objects": ["jeans_101", "bottom_cabinet_1"], "value": true}], "sub_segments": []}, {"start": 3261, "end": 3284, "duration": 23, "state_records": [{"name": "Inside", "objects": ["jeans_101", "bottom_cabinet_1"], "value": true}], "sub_segments": []}, {"start": 3284, "end": 3535, "duration": 251, "state_records": [{"name": "InHandOfRobot", "objects": ["jeans_100"], "value": true}], "sub_segments": []}, {"start": 3535, "end": 3694, "duration": 159, "state_records": [{"name": "Inside", "objects": ["jeans_100", "bottom_cabinet_6"], "value": true}], "sub_segments": []}, {"start": 3694, "end": 3697, "duration": 3, "state_records": [{"name": "OnTop", "objects": ["jeans_100", "bottom_cabinet_6"], "value": true}], "sub_segments": []}, {"start": 3697, "end": 3714, "duration": 17, "state_records": [{"name": "Open", "objects": ["bottom_cabinet_6"], "value": false}], "sub_segments": []}, {"start": 3714, "end": 3908, "duration": 194, "state_records": [{"name": "OnFloor", "objects": ["hand_towel_106", "room_floor_bedroom_0"], "value": true}], "sub_segments": []}, {"start": 3908, "end": 3920, "duration": 12, "state_records": [{"name": "InHandOfRobot", "objects": ["hand_towel_106"], "value": true}], "sub_segments": []}, {"start": 3920, "end": 4066, "duration": 146, "state_records": [{"name": "OnTop", "objects": ["hand_towel_106", "bottom_cabinet_1"], "value": true}], "sub_segments": []}, {"start": 4066, "end": 4128, "duration": 62, "state_records": [{"name": "OnTop", "objects": ["hand_towel_106", "room_floor_bedroom_0"], "value": true}, {"name": "OnFloor", "objects": ["hand_towel_106", "room_floor_bedroom_0"], "value": true}], "sub_segments": []}, {"start": 4128, "end": 4209, "duration": 81, "state_records": [{"name": "Inside", "objects": ["hand_towel_106", "bottom_cabinet_1"], "value": true}], "sub_segments": []}, {"start": 4209, "end": 4216, "duration": 7, "state_records": [{"name": "OnTop", "objects": ["hand_towel_106", "bottom_cabinet_1"], "value": true}], "sub_segments": []}, {"start": 4216, "end": 4220, "duration": 4, "state_records": [{"name": "Inside", "objects": ["hand_towel_106", "bottom_cabinet_1"], "value": true}], "sub_segments": []}, {"start": 4220, "end": 4517, "duration": 297, "state_records": [{"name": "OnTop", "objects": ["hand_towel_106", "room_floor_bedroom_0"], "value": true}, {"name": "OnFloor", "objects": ["hand_towel_106", "room_floor_bedroom_0"], "value": true}], "sub_segments": []}, {"start": 4517, "end": 4555, "duration": 38, "state_records": [{"name": "OnTop", "objects": ["hand_towel_106", "bottom_cabinet_6"], "value": true}], "sub_segments": []}, {"start": 4555, "end": 4764, "duration": 209, "state_records": [{"name": "Open", "objects": ["bottom_cabinet_6"], "value": true}], "sub_segments": []}, {"start": 4764, "end": 4855, "duration": 91, "state_records": [{"name": "OnTop", "objects": ["hand_towel_106", "bottom_cabinet_6"], "value": true}], "sub_segments": []}, {"start": 4855, "end": 4883, "duration": 28, "state_records": [{"name": "Inside", "objects": ["hand_towel_106", "bottom_cabinet_6"], "value": true}], "sub_segments": []}, {"start": 4883, "end": 4935, "duration": 52, "state_records": [{"name": "Open", "objects": ["bottom_cabinet_6"], "value": false}], "sub_segments": []}, {"start": 4935, "end": 4963, "duration": 28, "state_records": [{"name": "Open", "objects": ["bottom_cabinet_6"], "value": true}], "sub_segments": []}, {"start": 4963, "end": 5012, "duration": 49, "state_records": [{"name": "OnTop", "objects": ["hand_towel_106", "bottom_cabinet_6"], "value": true}, {"name": "Inside", "objects": ["hand_towel_106", "bottom_cabinet_6"], "value": true}], "sub_segments": []}, {"start": 5012, "end": 5037, "duration": 25, "state_records": [{"name": "Open", "objects": ["bottom_cabinet_6"], "value": false}], "sub_segments": []}, {"start": 5037, "end": 5060, "duration": 23, "state_records": [{"name": "OnTop", "objects": ["hand_towel_106", "room_floor_bedroom_0"], "value": true}, {"name": "OnFloor", "objects": ["hand_towel_106", "room_floor_bedroom_0"], "value": true}], "sub_segments": []}]}}}