{"deterministic": true, "task": "cleaning_the_hot_tub", "task_id": 0, "scene": "Ihlen_0_int", "task_done": true, "total_frame_num": 2400, "failed": false, "filename": "cleaning_the_hot_tub_0_Ihlen_0_int_2021-09-11_13-43-17.hdf5", "segmentations": {"flat": {"start": 1, "end": 1615, "duration": 1614, "state_records": [], "sub_segments": [{"start": 1, "end": 506, "duration": 505, "state_records": [{"name": "InHandOfRobot", "objects": ["scrub_brush_51"], "value": true}], "sub_segments": []}, {"start": 506, "end": 946, "duration": 440, "state_records": [{"name": "OnFloor", "objects": ["pool_50", "room_floor_garage_0"], "value": true}], "sub_segments": []}, {"start": 946, "end": 1075, "duration": 129, "state_records": [{"name": "Open", "objects": ["door_47"], "value": true}], "sub_segments": []}, {"start": 1075, "end": 1116, "duration": 41, "state_records": [{"name": "Inside", "objects": ["door_47", "scrub_brush_51"], "value": true}], "sub_segments": []}, {"start": 1116, "end": 1615, "duration": 499, "state_records": [{"name": "OnTop", "objects": ["scrub_brush_51", "pool_50"], "value": true}], "sub_segments": []}]}}}